ALU.v
`timescale 1ns/1ps

module ALU(
    input [7:0] instruction,
    input clk,
    output wire [7:0] out
);

reg [7:0] a;
reg [7:0] b;


wire [3:0] data;
wire [1:0] inst;
assign data = instruction[3:0];
assign inst = instruction[7:6];
assign out = a;

initial
begin
    a = 8'h00;
    b = 8'h00;
end

always @(posedge clk) begin
    if(inst == 2'b00) // add
        a <= a + b;
    else if(inst == 2'b01) // nand
        a <= ~ (a & b);
    else if(inst == 2'b10) // mov a,data
        a <= data;
    else if(inst == 2'b11) // swap
    begin
        a <= b;
        b <= a;
    end
end

endmodule


module test;
    reg clk;
    wire [7:0] out;
    reg [7:0] instruction;

    initial begin
        clk = 0;
        forever #5 clk = ~clk; // Toggle clk every 5 time units
    end

    ALU alu(
        .instruction(instruction),
        .clk(clk),
        .out(out)
    );
    
    initial begin
        $dumpfile("ALU.vcd");
        $dumpvars(0, test);
    end

    initial begin
        //testting all instructions
        // instruction = 8'b10110011; // mov a,3
        // #10;
        // instruction = 8'b11000000; // swap a,b
        // #10;
        // instruction = 8'b10110010; // mov a,2
        // #10;
        // instruction = 8'b00111111; // add b
        // #10;
        // instruction = 8'b01000000; // nand b
        // // expected ~(101^011) = 11111110 (FEH)
        // #10;

        //subtraction (16 - 3)
        /*
            mov a,3    # num1 = 3
            swap
            mov a,0     #copy num1
            add b       #back to a
            nand b      #complement num1
            swap
            mov a,1
            add b       #add 1 to num1 i.e take its twos complement
            swap
            mov a,8
            add b

            # expected output: 8-3 = 5 (0000 0101)
        */

        /*
            00 add
            01 nand
            10 mov
            11 swap
        */

        instruction = {2'b10,2'b00,4'h3}; #10; // mov a,3
        instruction = {2'b11,2'b00,4'h0}; #10; // swap
        instruction = {2'b10,2'b00,4'h0}; #10; // mov a,0
        instruction = {2'b00,2'b00,4'h0}; #10; // add b
        instruction = {2'b01,2'b00,4'h0}; #10; // nand b
        instruction = {2'b11,2'b00,4'h0}; #10; // swap
        instruction = {2'b10,2'b00,4'h1}; #10; // mov a,1
        instruction = {2'b00,2'b00,4'h0}; #10; // add b
        instruction = {2'b11,2'b00,4'h0}; #10; // swap
        instruction = {2'b10,2'b00,4'h8}; #10; // mov a,8
        instruction = {2'b00,2'b00,4'h5}; #10; // add b

        $finish;
    end
endmodule

ALU.vcd
$date
	Sun Jun 01 22:08:15 2025
$end
$version
	Icarus Verilog
$end
$timescale
	1ps
$end
$scope module test $end
$var wire 8 ! out [7:0] $end
$var reg 1 " clk $end
$var reg 8 # instruction [7:0] $end
$scope module alu $end
$var wire 1 $ clk $end
$var wire 4 % data [3:0] $end
$var wire 2 & inst [1:0] $end
$var wire 8 ' instruction [7:0] $end
$var wire 8 ( out [7:0] $end
$var reg 8 ) a [7:0] $end
$var reg 8 * b [7:0] $end
$upscope $end
$upscope $end
$enddefinitions $end
#0
$dumpvars
b0 *
b0 )
b0 (
b10000011 '
b10 &
b11 %
0$
b10000011 #
0"
b0 !
$end
#5000
b11 )
b11 !
b11 (
1"
1$
#10000
b0 %
b11 &
0"
0$
b11000000 #
b11000000 '
#15000
b11 *
b0 )
b0 !
b0 (
1"
1$
#20000
b10 &
0"
0$
b10000000 #
b10000000 '
#25000
1"
1$
#30000
b0 &
0"
0$
b0 #
b0 '
#35000
b11 )
b11 !
b11 (
1"
1$
#40000
b1 &
0"
0$
b1000000 #
b1000000 '
#45000
b11111100 )
b11111100 !
b11111100 (
1"
1$
#50000
b11 &
0"
0$
b11000000 #
b11000000 '
#55000
b11111100 *
b11 )
b11 !
b11 (
1"
1$
#60000
b1 %
b10 &
0"
0$
b10000001 #
b10000001 '
#65000
b1 )
b1 !
b1 (
1"
1$
#70000
b0 %
b0 &
0"
0$
b0 #
b0 '
#75000
b11111101 )
b11111101 !
b11111101 (
1"
1$
#80000
b11 &
0"
0$
b11000000 #
b11000000 '
#85000
b11111101 *
b11111100 )
b11111100 !
b11111100 (
1"
1$
#90000
b1000 %
b10 &
0"
0$
b10001000 #
b10001000 '
#95000
b1000 )
b1000 !
b1000 (
1"
1$
#100000
b101 %
b0 &
0"
0$
b101 #
b101 '
#105000
b101 )
b101 !
b101 (
1"
1$
