Multiplier.v
`timescale 1ns/1ps

module Multiplier (
    input [7:0] a,
    input [7:0] b,
    output wire [15:0] c
);

wire [15:0] p0 = (b[0] == 1) ? a : 0;
wire [15:0] p1 = (b[1] == 1) ? (a << 1) : 0;
wire [15:0] p2 = (b[2] == 1) ? (a << 2) : 0;
wire [15:0] p3 = (b[3] == 1) ? (a << 3) : 0;
wire [15:0] p4 = (b[4] == 1) ? (a << 4) : 0;
wire [15:0] p5 = (b[5] == 1) ? (a << 5) : 0;
wire [15:0] p6 = (b[6] == 1) ? (a << 6) : 0;
wire [15:0] p7 = (b[7] == 1) ? (a << 7) : 0;

assign c = p0 + p1 + p2 + p3 + p4 + p5 + p6 + p7;

endmodule

module test;
    reg clk;
    reg [3:0] a, b;
    wire [15:0] product;

    Multiplier multiplier (
        .a(a),
        .b(b),
        .c(product)
    );

    initial begin
        a = 4'b0000; // Initialize a to 0
        b = 4'b0000; // Initialize b to 0
    end

    initial begin
        clk = 0;
        forever #5 clk = ~clk; // Toggle clk every 5 time units
    end

    always @(posedge clk) begin
        a <= a + 1; // Increment a on each clock edge
        b <= b + 1; // Increment b on each clock edge
    end

    initial begin
        $dumpfile("Multiplier.vcd");
        $dumpvars(0,test);
    end

    initial begin
        // $monitor("At time %0t, clk = %b, a = %b, b = %b, prod = %product", $time, clk, a, b, product);
        #100 $finish;
    end
endmodule

Multiplier.vcd
$date
	Wed Jun 11 13:51:08 2025
$end
$version
	Icarus Verilog
$end
$timescale
	1ps
$end
$scope module test $end
$var wire 16 ! product [15:0] $end
$var reg 4 " a [3:0] $end
$var reg 4 # b [3:0] $end
$var reg 1 $ clk $end
$scope module multiplier $end
$var wire 8 % a [7:0] $end
$var wire 8 & b [7:0] $end
$var wire 16 ' c [15:0] $end
$var wire 16 ( p0 [15:0] $end
$var wire 16 ) p1 [15:0] $end
$var wire 16 * p2 [15:0] $end
$var wire 16 + p3 [15:0] $end
$var wire 16 , p4 [15:0] $end
$var wire 16 - p5 [15:0] $end
$var wire 16 . p6 [15:0] $end
$var wire 16 / p7 [15:0] $end
$upscope $end
$upscope $end
$enddefinitions $end
#0
$dumpvars
b0 /
b0 .
b0 -
b0 ,
b0 +
b0 *
b0 )
b0 (
b0 '
b0 &
b0 %
0$
b0 #
b0 "
b0 !
$end
#5000
b1 !
b1 '
b1 (
b1 #
b1 &
b1 "
b1 %
1$
#10000
0$
#15000
b100 )
b100 !
b100 '
b0 (
b10 #
b10 &
b10 "
b10 %
1$
#20000
0$
#25000
b110 )
b1001 !
b1001 '
b11 (
b11 #
b11 &
b11 "
b11 %
1$
#30000
0$
#35000
b10000 *
b0 )
b10000 !
b10000 '
b0 (
b100 #
b100 &
b100 "
b100 %
1$
#40000
0$
#45000
b10100 *
b11001 !
b11001 '
b101 (
b101 #
b101 &
b101 "
b101 %
1$
#50000
0$
#55000
b1100 )
b11000 *
b100100 !
b100100 '
b0 (
b110 #
b110 &
b110 "
b110 %
1$
#60000
0$
#65000
b1110 )
b11100 *
b110001 !
b110001 '
b111 (
b111 #
b111 &
b111 "
b111 %
1$
#70000
0$
#75000
b1000000 +
b0 )
b0 *
b1000000 !
b1000000 '
b0 (
b1000 #
b1000 &
b1000 "
b1000 %
1$
#80000
0$
#85000
b1001000 +
b1010001 !
b1010001 '
b1001 (
b1001 #
b1001 &
b1001 "
b1001 %
1$
#90000
0$
#95000
b10100 )
b1010000 +
b1100100 !
b1100100 '
b0 (
b1010 #
b1010 &
b1010 "
b1010 %
1$
